{
  "name": "אסתר לוקשינסקי",
  "bio": "מלווה בתהליכי התפתחות אישית ברוח מיינדפולנס",
  "profilePicture": "/EstherLockshinsky.jpg",
  "roundProfilePicture": true,
  "url": "https://linktower.mitchellwallace.net",
  "language": "he",
  "direction": "rtl",
  "theme": "spiritual",
  "isBlogDisplayed": false,
  "blogHomePostLimit": 3,
  "contactFormEnabled": false,
  "web3FormsAccessKey": "",
  "umamiWebsiteId": "",
  "iconLinks": [
    {
      "id": "facebook-icon",
      "icon": "logos:facebook",
      "url": "https://www.facebook.com/profile.php?id=61578346152629#",
      "color": "base"
    },
    {
      "id": "whatsapp-icon",
      "icon": "logos:whatsapp-icon",
      "url": "https://chat.whatsapp.com/GvGRnhp3wBRIeCM30ePSPB?mode=gi_t",
      "color": "base"
    },
    {
      "id": "instagram-icon",
      "icon": "logos:instagram-icon",
      "url": "https://www.instagram.com/estherlockshinsky",
      "color": "base"
    }
  ],
  "customLinks": [
    {
      "title": "פייסבוק",
      "description": "עמוד הפייסבוק שלי",
      "url": "https://www.facebook.com/profile.php?id=61578346152629#",
      "icon": "logos:facebook",
      "color": "base",
      "newTab": true
    },
    {
      "title": "וואטסאפ",
      "description": "הצטרפו לקבוצת המאושרות שלי בוואטסאפ",
      "url": "https://chat.whatsapp.com/GvGRnhp3wBRIeCM30ePSPB?mode=gi_t",
      "icon": "logos:whatsapp-icon",
      "color": "base",
      "newTab": true
    },
    {
      "title": "אינסטגרם",
      "description": "עקבו אחרי באינסטגרם",
      "url": "https://www.instagram.com/estherlockshinsky",
      "icon": "logos:instagram-icon",
      "color": "base",
      "newTab": true
    }
  ]
}
